adaendra_python_config_loader/AdaendraConfigs.py
adaendra_python_config_loader/AdaendraConfigsLoader.py
adaendra_python_config_loader/Constants.py
adaendra_python_config_loader/__init__.py
adaendra_python_config_loader-1.0.0.dist-info/LICENSE
adaendra_python_config_loader-1.0.0.dist-info/METADATA
adaendra_python_config_loader-1.0.0.dist-info/WHEEL
adaendra_python_config_loader-1.0.0.dist-info/top_level.txt
adaendra_python_config_loader-1.0.0.dist-info/RECORD
