Metadata-Version: 2.1
Name: adaendra-python-config-loader
Version: 1.0.0
Summary: A config loader for Python projects
Home-page: https://github.com/Adaendra/python-config-loader
Author: Maxime G.
License: UNKNOWN
Project-URL: Bug Tracker, https://github.com/Adaendra/python-config-loader/issues
Platform: UNKNOWN
Classifier: Programming Language :: Python :: 3
Classifier: License :: OSI Approved :: GNU General Public License v3 (GPLv3)
Classifier: Operating System :: OS Independent
Requires-Python: >=3.6
License-File: LICENSE
